pycgp/geometry_reader.py
pycgp/cgp_config.py
pycgp/__init__.py
pycgp/cartesian_point_set.py
pycgp/topological_point_set.py
pycgp-0.1.2.dev0.dist-info/METADATA
pycgp-0.1.2.dev0.dist-info/top_level.txt
pycgp-0.1.2.dev0.dist-info/WHEEL
pycgp-0.1.2.dev0.dist-info/DESCRIPTION.rst
pycgp-0.1.2.dev0.dist-info/RECORD
pycgp-0.1.2.dev0.dist-info/metadata.json
