Metadata-Version: 2.0
Name: pycgp
Version: 0.1.2.dev0
Summary: Python reader for CGP files
Home-page: https://github.com/tobiasmaier/pycgp
Author: Tobias Maier
Author-email: tobias.maier@unibas.ch
License: BSD 3-clause
Platform: UNKNOWN
Classifier: Development Status :: 4 - Beta
Classifier: Environment :: Console
Classifier: Intended Audience :: Developers
Classifier: Intended Audience :: Science/Research
Classifier: License :: OSI Approved :: BSD License
Classifier: Programming Language :: Python
Classifier: Programming Language :: Python :: 3
Classifier: Topic :: Scientific/Engineering
Classifier: Operating System :: Microsoft :: Windows
Classifier: Operating System :: POSIX
Classifier: Operating System :: Unix
Classifier: Operating System :: MacOS
